{
  "manifestVersion": "3.2",
  "admin": {
    "address": "0xbf25b58cB8DfaD688F7BcB2b87D71C23A6600AaC",
    "txHash": "0xe9deb2f610ed3d04a199572b57fb22f39e84084e2b2ccd9ee75b31252dcd9ce7"
  },
  "proxies": [
    {
      "address": "0x0312A9D1Ff2372DDEdCBB21e4B6389aFc919aC4B",
      "txHash": "0x016f2c3dcdb0ef8474a14e77377ee5d4cdebc958daba8028188262a85062c45b",
      "kind": "transparent"
    },
    {
      "address": "0xDD629E5241CbC5919847783e6C96B2De4754e438",
      "txHash": "0xaa53d500c0c608dfdc1104b3a7652974acfbe5fad61f6b66873464a6892b6576",
      "kind": "transparent"
    },
    {
      "address": "0x2247B5A46BB79421a314aB0f0b67fFd11dd37Ee4",
      "txHash": "0x30580ef67e71b61d4bcf423f554f9f2d2876b4a55a94ab3af347cba47d56dbde",
      "kind": "transparent"
    }
  ],
  "impls": {
    "ae32fc7ffebdd4e85444fa3c7867da34172c9cc50c1e7cc8b7f046b6f1049605": {
      "address": "0xEFb2E28b69A29A39067b20aF633d04A2857a4D9d",
      "txHash": "0x5615ce281ce618e8ec9b55803ee932312ab731a10c37ccce2b83fa02c4d2acd3",
      "layout": {
        "solcVersion": "0.8.9",
        "storage": [
          {
            "label": "_initialized",
            "offset": 0,
            "slot": "0",
            "type": "t_uint8",
            "contract": "Initializable",
            "src": "@openzeppelin/contracts-upgradeable/proxy/utils/Initializable.sol:63",
            "retypedFrom": "bool"
          },
          {
            "label": "_initializing",
            "offset": 1,
            "slot": "0",
            "type": "t_bool",
            "contract": "Initializable",
            "src": "@openzeppelin/contracts-upgradeable/proxy/utils/Initializable.sol:68"
          },
          {
            "label": "__gap",
            "offset": 0,
            "slot": "1",
            "type": "t_array(t_uint256)50_storage",
            "contract": "ContextUpgradeable",
            "src": "@openzeppelin/contracts-upgradeable/utils/ContextUpgradeable.sol:36"
          },
          {
            "label": "__gap",
            "offset": 0,
            "slot": "51",
            "type": "t_array(t_uint256)50_storage",
            "contract": "ERC165Upgradeable",
            "src": "@openzeppelin/contracts-upgradeable/utils/introspection/ERC165Upgradeable.sol:41"
          },
          {
            "label": "_roles",
            "offset": 0,
            "slot": "101",
            "type": "t_mapping(t_bytes32,t_struct(RoleData)80_storage)",
            "contract": "AccessControlUpgradeable",
            "src": "@openzeppelin/contracts-upgradeable/access/AccessControlUpgradeable.sol:62"
          },
          {
            "label": "__gap",
            "offset": 0,
            "slot": "102",
            "type": "t_array(t_uint256)49_storage",
            "contract": "AccessControlUpgradeable",
            "src": "@openzeppelin/contracts-upgradeable/access/AccessControlUpgradeable.sol:260"
          }
        ],
        "types": {
          "t_address": {
            "label": "address",
            "numberOfBytes": "20"
          },
          "t_array(t_uint256)49_storage": {
            "label": "uint256[49]",
            "numberOfBytes": "1568"
          },
          "t_array(t_uint256)50_storage": {
            "label": "uint256[50]",
            "numberOfBytes": "1600"
          },
          "t_bool": {
            "label": "bool",
            "numberOfBytes": "1"
          },
          "t_bytes32": {
            "label": "bytes32",
            "numberOfBytes": "32"
          },
          "t_mapping(t_address,t_bool)": {
            "label": "mapping(address => bool)",
            "numberOfBytes": "32"
          },
          "t_mapping(t_bytes32,t_struct(RoleData)80_storage)": {
            "label": "mapping(bytes32 => struct AccessControlUpgradeable.RoleData)",
            "numberOfBytes": "32"
          },
          "t_struct(RoleData)80_storage": {
            "label": "struct AccessControlUpgradeable.RoleData",
            "members": [
              {
                "label": "members",
                "type": "t_mapping(t_address,t_bool)",
                "offset": 0,
                "slot": "0"
              },
              {
                "label": "adminRole",
                "type": "t_bytes32",
                "offset": 0,
                "slot": "1"
              }
            ],
            "numberOfBytes": "64"
          },
          "t_uint256": {
            "label": "uint256",
            "numberOfBytes": "32"
          },
          "t_uint8": {
            "label": "uint8",
            "numberOfBytes": "1"
          }
        }
      }
    },
    "0bcd27c8aec887ed9edec297f766c8e26dad1577ef83ca91bdae74594d8f4afc": {
      "address": "0xefED40D1eb1577d1073e9C4F277463486D39b084",
      "txHash": "0xe0f7c18e7ca69e6c692c91f818253a749386dffdc2d1e17b40991d4c3f5f4802",
      "layout": {
        "solcVersion": "0.8.9",
        "storage": [
          {
            "label": "_initialized",
            "offset": 0,
            "slot": "0",
            "type": "t_uint8",
            "contract": "Initializable",
            "src": "@openzeppelin/contracts-upgradeable/proxy/utils/Initializable.sol:63",
            "retypedFrom": "bool"
          },
          {
            "label": "_initializing",
            "offset": 1,
            "slot": "0",
            "type": "t_bool",
            "contract": "Initializable",
            "src": "@openzeppelin/contracts-upgradeable/proxy/utils/Initializable.sol:68"
          },
          {
            "label": "__gap",
            "offset": 0,
            "slot": "1",
            "type": "t_array(t_uint256)50_storage",
            "contract": "ContextUpgradeable",
            "src": "@openzeppelin/contracts-upgradeable/utils/ContextUpgradeable.sol:36"
          },
          {
            "label": "_balances",
            "offset": 0,
            "slot": "51",
            "type": "t_mapping(t_address,t_uint256)",
            "contract": "ERC20Upgradeable",
            "src": "@openzeppelin/contracts-upgradeable/token/ERC20/ERC20Upgradeable.sol:40"
          },
          {
            "label": "_allowances",
            "offset": 0,
            "slot": "52",
            "type": "t_mapping(t_address,t_mapping(t_address,t_uint256))",
            "contract": "ERC20Upgradeable",
            "src": "@openzeppelin/contracts-upgradeable/token/ERC20/ERC20Upgradeable.sol:42"
          },
          {
            "label": "_totalSupply",
            "offset": 0,
            "slot": "53",
            "type": "t_uint256",
            "contract": "ERC20Upgradeable",
            "src": "@openzeppelin/contracts-upgradeable/token/ERC20/ERC20Upgradeable.sol:44"
          },
          {
            "label": "_name",
            "offset": 0,
            "slot": "54",
            "type": "t_string_storage",
            "contract": "ERC20Upgradeable",
            "src": "@openzeppelin/contracts-upgradeable/token/ERC20/ERC20Upgradeable.sol:46"
          },
          {
            "label": "_symbol",
            "offset": 0,
            "slot": "55",
            "type": "t_string_storage",
            "contract": "ERC20Upgradeable",
            "src": "@openzeppelin/contracts-upgradeable/token/ERC20/ERC20Upgradeable.sol:47"
          },
          {
            "label": "__gap",
            "offset": 0,
            "slot": "56",
            "type": "t_array(t_uint256)45_storage",
            "contract": "ERC20Upgradeable",
            "src": "@openzeppelin/contracts-upgradeable/token/ERC20/ERC20Upgradeable.sol:376"
          },
          {
            "label": "_paused",
            "offset": 0,
            "slot": "101",
            "type": "t_bool",
            "contract": "PausableUpgradeable",
            "src": "@openzeppelin/contracts-upgradeable/security/PausableUpgradeable.sol:29"
          },
          {
            "label": "__gap",
            "offset": 0,
            "slot": "102",
            "type": "t_array(t_uint256)49_storage",
            "contract": "PausableUpgradeable",
            "src": "@openzeppelin/contracts-upgradeable/security/PausableUpgradeable.sol:116"
          },
          {
            "label": "__gap",
            "offset": 0,
            "slot": "151",
            "type": "t_array(t_uint256)50_storage",
            "contract": "ERC20PausableUpgradeable",
            "src": "@openzeppelin/contracts-upgradeable/token/ERC20/extensions/ERC20PausableUpgradeable.sol:48"
          },
          {
            "label": "accessControl",
            "offset": 0,
            "slot": "201",
            "type": "t_contract(MidasAccessControl)10482",
            "contract": "WithMidasAccessControl",
            "src": "contracts/access/WithMidasAccessControl.sol:24"
          },
          {
            "label": "__gap",
            "offset": 0,
            "slot": "202",
            "type": "t_array(t_uint256)50_storage",
            "contract": "WithMidasAccessControl",
            "src": "contracts/access/WithMidasAccessControl.sol:29"
          },
          {
            "label": "__gap",
            "offset": 0,
            "slot": "252",
            "type": "t_array(t_uint256)50_storage",
            "contract": "Blacklistable",
            "src": "contracts/access/Blacklistable.sol:16"
          },
          {
            "label": "metadata",
            "offset": 0,
            "slot": "302",
            "type": "t_mapping(t_bytes32,t_bytes_storage)",
            "contract": "mTBILL",
            "src": "contracts/mTBILL/mTBILL.sol:18"
          },
          {
            "label": "__gap",
            "offset": 0,
            "slot": "303",
            "type": "t_array(t_uint256)50_storage",
            "contract": "mTBILL",
            "src": "contracts/mTBILL/mTBILL.sol:23"
          }
        ],
        "types": {
          "t_address": {
            "label": "address",
            "numberOfBytes": "20"
          },
          "t_array(t_uint256)45_storage": {
            "label": "uint256[45]",
            "numberOfBytes": "1440"
          },
          "t_array(t_uint256)49_storage": {
            "label": "uint256[49]",
            "numberOfBytes": "1568"
          },
          "t_array(t_uint256)50_storage": {
            "label": "uint256[50]",
            "numberOfBytes": "1600"
          },
          "t_bool": {
            "label": "bool",
            "numberOfBytes": "1"
          },
          "t_bytes32": {
            "label": "bytes32",
            "numberOfBytes": "32"
          },
          "t_bytes_storage": {
            "label": "bytes",
            "numberOfBytes": "32"
          },
          "t_contract(MidasAccessControl)10482": {
            "label": "contract MidasAccessControl",
            "numberOfBytes": "20"
          },
          "t_mapping(t_address,t_mapping(t_address,t_uint256))": {
            "label": "mapping(address => mapping(address => uint256))",
            "numberOfBytes": "32"
          },
          "t_mapping(t_address,t_uint256)": {
            "label": "mapping(address => uint256)",
            "numberOfBytes": "32"
          },
          "t_mapping(t_bytes32,t_bytes_storage)": {
            "label": "mapping(bytes32 => bytes)",
            "numberOfBytes": "32"
          },
          "t_string_storage": {
            "label": "string",
            "numberOfBytes": "32"
          },
          "t_uint256": {
            "label": "uint256",
            "numberOfBytes": "32"
          },
          "t_uint8": {
            "label": "uint8",
            "numberOfBytes": "1"
          }
        }
      }
    },
    "457139d45838add2b3b60a093a44deb231aeaff72de5455cf12e9b9019de483e": {
      "address": "0xc5412dc7e87570ec18803bbb33549FD94f9D611e",
      "txHash": "0x4b1fb80848f1663d37dd52191af8ecf25d547b495dade6a8c345324714654efb",
      "layout": {
        "solcVersion": "0.8.9",
        "storage": [
          {
            "label": "_initialized",
            "offset": 0,
            "slot": "0",
            "type": "t_uint8",
            "contract": "Initializable",
            "src": "@openzeppelin/contracts-upgradeable/proxy/utils/Initializable.sol:63",
            "retypedFrom": "bool"
          },
          {
            "label": "_initializing",
            "offset": 1,
            "slot": "0",
            "type": "t_bool",
            "contract": "Initializable",
            "src": "@openzeppelin/contracts-upgradeable/proxy/utils/Initializable.sol:68"
          },
          {
            "label": "__gap",
            "offset": 0,
            "slot": "1",
            "type": "t_array(t_uint256)50_storage",
            "contract": "ContextUpgradeable",
            "src": "@openzeppelin/contracts-upgradeable/utils/ContextUpgradeable.sol:36"
          },
          {
            "label": "_balances",
            "offset": 0,
            "slot": "51",
            "type": "t_mapping(t_address,t_uint256)",
            "contract": "ERC20Upgradeable",
            "src": "@openzeppelin/contracts-upgradeable/token/ERC20/ERC20Upgradeable.sol:40"
          },
          {
            "label": "_allowances",
            "offset": 0,
            "slot": "52",
            "type": "t_mapping(t_address,t_mapping(t_address,t_uint256))",
            "contract": "ERC20Upgradeable",
            "src": "@openzeppelin/contracts-upgradeable/token/ERC20/ERC20Upgradeable.sol:42"
          },
          {
            "label": "_totalSupply",
            "offset": 0,
            "slot": "53",
            "type": "t_uint256",
            "contract": "ERC20Upgradeable",
            "src": "@openzeppelin/contracts-upgradeable/token/ERC20/ERC20Upgradeable.sol:44"
          },
          {
            "label": "_name",
            "offset": 0,
            "slot": "54",
            "type": "t_string_storage",
            "contract": "ERC20Upgradeable",
            "src": "@openzeppelin/contracts-upgradeable/token/ERC20/ERC20Upgradeable.sol:46"
          },
          {
            "label": "_symbol",
            "offset": 0,
            "slot": "55",
            "type": "t_string_storage",
            "contract": "ERC20Upgradeable",
            "src": "@openzeppelin/contracts-upgradeable/token/ERC20/ERC20Upgradeable.sol:47"
          },
          {
            "label": "__gap",
            "offset": 0,
            "slot": "56",
            "type": "t_array(t_uint256)45_storage",
            "contract": "ERC20Upgradeable",
            "src": "@openzeppelin/contracts-upgradeable/token/ERC20/ERC20Upgradeable.sol:376"
          },
          {
            "label": "_paused",
            "offset": 0,
            "slot": "101",
            "type": "t_bool",
            "contract": "PausableUpgradeable",
            "src": "@openzeppelin/contracts-upgradeable/security/PausableUpgradeable.sol:29"
          },
          {
            "label": "__gap",
            "offset": 0,
            "slot": "102",
            "type": "t_array(t_uint256)49_storage",
            "contract": "PausableUpgradeable",
            "src": "@openzeppelin/contracts-upgradeable/security/PausableUpgradeable.sol:116"
          },
          {
            "label": "__gap",
            "offset": 0,
            "slot": "151",
            "type": "t_array(t_uint256)50_storage",
            "contract": "ERC20PausableUpgradeable",
            "src": "@openzeppelin/contracts-upgradeable/token/ERC20/extensions/ERC20PausableUpgradeable.sol:48"
          },
          {
            "label": "accessControl",
            "offset": 0,
            "slot": "201",
            "type": "t_contract(MidasAccessControl)10482",
            "contract": "WithMidasAccessControl",
            "src": "contracts/access/WithMidasAccessControl.sol:24"
          },
          {
            "label": "__gap",
            "offset": 0,
            "slot": "202",
            "type": "t_array(t_uint256)50_storage",
            "contract": "WithMidasAccessControl",
            "src": "contracts/access/WithMidasAccessControl.sol:29"
          },
          {
            "label": "__gap",
            "offset": 0,
            "slot": "252",
            "type": "t_array(t_uint256)50_storage",
            "contract": "Blacklistable",
            "src": "contracts/access/Blacklistable.sol:16"
          },
          {
            "label": "metadata",
            "offset": 0,
            "slot": "302",
            "type": "t_mapping(t_bytes32,t_bytes_storage)",
            "contract": "mTBILL",
            "src": "contracts/mTBILL/mTBILL.sol:18"
          },
          {
            "label": "__gap",
            "offset": 0,
            "slot": "303",
            "type": "t_array(t_uint256)50_storage",
            "contract": "mTBILL",
            "src": "contracts/mTBILL/mTBILL.sol:23"
          },
          {
            "label": "__gap",
            "offset": 0,
            "slot": "353",
            "type": "t_array(t_uint256)50_storage",
            "contract": "mBASIS",
            "src": "contracts/mBasis/mBASIS.sol:32"
          }
        ],
        "types": {
          "t_address": {
            "label": "address",
            "numberOfBytes": "20"
          },
          "t_array(t_uint256)45_storage": {
            "label": "uint256[45]",
            "numberOfBytes": "1440"
          },
          "t_array(t_uint256)49_storage": {
            "label": "uint256[49]",
            "numberOfBytes": "1568"
          },
          "t_array(t_uint256)50_storage": {
            "label": "uint256[50]",
            "numberOfBytes": "1600"
          },
          "t_bool": {
            "label": "bool",
            "numberOfBytes": "1"
          },
          "t_bytes32": {
            "label": "bytes32",
            "numberOfBytes": "32"
          },
          "t_bytes_storage": {
            "label": "bytes",
            "numberOfBytes": "32"
          },
          "t_contract(MidasAccessControl)10482": {
            "label": "contract MidasAccessControl",
            "numberOfBytes": "20"
          },
          "t_mapping(t_address,t_mapping(t_address,t_uint256))": {
            "label": "mapping(address => mapping(address => uint256))",
            "numberOfBytes": "32"
          },
          "t_mapping(t_address,t_uint256)": {
            "label": "mapping(address => uint256)",
            "numberOfBytes": "32"
          },
          "t_mapping(t_bytes32,t_bytes_storage)": {
            "label": "mapping(bytes32 => bytes)",
            "numberOfBytes": "32"
          },
          "t_string_storage": {
            "label": "string",
            "numberOfBytes": "32"
          },
          "t_uint256": {
            "label": "uint256",
            "numberOfBytes": "32"
          },
          "t_uint8": {
            "label": "uint8",
            "numberOfBytes": "1"
          }
        }
      }
    }
  }
}
